anaconda_toolbox/__init__.py
anaconda_toolbox-0.0.1.dist-info/METADATA
anaconda_toolbox-0.0.1.dist-info/WHEEL
anaconda_toolbox-0.0.1.dist-info/RECORD
