Metadata-Version: 2.1
Name: anaconda-toolbox
Version: 0.0.1
Summary: Please install the anaconda-toolbox with conda
License-Expression: BSD-3-Clause
